{
  "controls": [
    {
      "id": "1d838e6b-9292-4648-be7a-45916bb5bce4",
      "typeId": "button",
      "properties": {
        "text.text": "A Button",
        "text.formatting": 2,
        "text.fontFamily": "",
        "text.size": 16,
        "text.alignment": "",
        "button.scripts.click": "alert(\"Thanks for Clicking\")"
      },
      "position": { "left": 512, "top": 288, "right": 152, "bottom": 480 }
    },
    {
      "id": "b93aa19b-6e8d-483e-bdb5-0b3610fe4cee",
      "typeId": "label",
      "properties": {
        "text.text": "This is an example of a layout created with the WYSIWYG application",
        "text.size": 15,
        "text.alignment": "left",
        "content.verticalAlignment": ""
      },
      "position": { "left": 24, "top": 56, "right": 256, "bottom": 712 }
    },
    {
      "id": "4a556d1b-ee86-4964-850a-1ab24e2d04f5",
      "typeId": "button",
      "properties": {
        "text.text": "Another Button",
        "text.fontFamily": "",
        "text.size": 16,
        "text.alignment": "",
        "button.scripts.click": "alert(\"You can edit the script of a button too!\")"
      },
      "position": { "left": 656, "top": 288, "right": 8, "bottom": 480 }
    },
    {
      "id": "5e619aa6-811e-499d-9488-77d7ae5b1377",
      "typeId": "label",
      "properties": {
        "text.text": "Only the \"Design\" portion of this app is complete - not the \"runtime\" part, so buttons aren't clickable (yet), but you can test the scripts associated with them",
        "text.size": 15,
        "text.alignment": "",
        "content.verticalAlignment": ""
      },
      "position": { "left": 24, "top": 96, "right": 264, "bottom": 648 }
    },
    {
      "id": "dffe6c74-1038-477c-a6fb-a2615ec73f17",
      "typeId": "label",
      "properties": {
        "text.text": "Example  Layout",
        "text.formatting": 2,
        "text.size": 25,
        "text.alignment": "",
        "content.verticalAlignment": "flex-start"
      },
      "position": { "left": 24, "top": 16, "right": 552, "bottom": 744 }
    },
    {
      "id": "cecdb64e-8f95-478d-a84a-3155ac4d6ff3",
      "typeId": "checkbox",
      "properties": {
        "text.text": "A checkbox",
        "text.size": 16,
        "text.alignment": "",
        "content.verticalAlignment": "",
        "checkbox.isChecked": true
      },
      "position": { "left": 16, "top": 288, "right": 480, "bottom": 480 }
    }
  ],
  "root": { "properties": { "control.backgroundColor": "" } }
}
